lbxtoolkit/__init__.py
lbxtoolkit/api_rest.py
lbxtoolkit/auth_entra_id.py
lbxtoolkit/config_manager.py
lbxtoolkit/lbx_logger.py
lbxtoolkit/misc.py
lbxtoolkit/postgresql.py
lbxtoolkit/service.py
lbxtoolkit/service_windows.py
lbxtoolkit-2.3.1.dist-info/METADATA
lbxtoolkit-2.3.1.dist-info/WHEEL
lbxtoolkit-2.3.1.dist-info/RECORD
