Metadata-Version: 2.3
Name: lbxtoolkit
Version: 2.3.1
Summary: 
Author: Cristiano P. Ferrari
Author-email: cristiano.ferrari@lbx.com.br
Requires-Python: >=3.12,<4.0
Classifier: Programming Language :: Python :: 3
Classifier: Programming Language :: Python :: 3.12
Classifier: Programming Language :: Python :: 3.13
Requires-Dist: msal (>=1.30.0)
Requires-Dist: numpy (>=2.0.1)
Requires-Dist: pandas (>=2.2.2)
Requires-Dist: psutil (>=6.0.0)
Requires-Dist: psycopg2 (>=2.9.9)
Requires-Dist: pygetwindow (>=0.0.9)
Requires-Dist: pywin32 (>=306)
Requires-Dist: requests (>=2.32.3)
Requires-Dist: selenium (>=4.23.1)
Requires-Dist: validators (>=0.33.0)
Requires-Dist: webdriver-manager (>=4.0.2)
